1d2402ac2cb686797a30__mypyc.cpython-39-x86_64-linux-gnu.so
stringmatch/__init__.cpython-39-x86_64-linux-gnu.so
stringmatch/__init__.py
stringmatch/distance.cpython-39-x86_64-linux-gnu.so
stringmatch/distance.py
stringmatch/match.cpython-39-x86_64-linux-gnu.so
stringmatch/match.py
stringmatch/py.typed
stringmatch/ratio.cpython-39-x86_64-linux-gnu.so
stringmatch/ratio.py
stringmatch/scorer.cpython-39-x86_64-linux-gnu.so
stringmatch/scorer.py
stringmatch/strings.cpython-39-x86_64-linux-gnu.so
stringmatch/strings.py
tests/__init__.py
tests/test_distance.py
tests/test_match.py
tests/test_ratio.py
tests/test_strings.py
stringmatch-0.14.7.dist-info/METADATA
stringmatch-0.14.7.dist-info/WHEEL
stringmatch-0.14.7.dist-info/top_level.txt
stringmatch-0.14.7.dist-info/RECORD
stringmatch-0.14.7.dist-info/licenses/LICENSE
