Metadata-Version: 2.4
Name: stringmatch
Version: 0.14.7
Summary: A library to match and compare strings.
Home-page: https://github.com/atomflunder/stringmatch
Author: atomflunder
Author-email: 80397293+atomflunder@users.noreply.github.com
License: MIT
Keywords: stringmatch string match fuzzy matching
Classifier: Development Status :: 3 - Alpha
Classifier: Intended Audience :: Developers
Classifier: License :: OSI Approved :: MIT License
Classifier: Natural Language :: English
Classifier: Operating System :: OS Independent
Classifier: Programming Language :: Python :: 3.9
Classifier: Programming Language :: Python :: 3.10
Classifier: Programming Language :: Python :: 3.11
Classifier: Programming Language :: Python :: 3.12
Classifier: Programming Language :: Python :: 3.13
Classifier: Programming Language :: Python :: 3.14
Requires-Python: >=3.9
License-File: LICENSE
Requires-Dist: rapidfuzz==3.13.0
Requires-Dist: unidecode==1.4.0
Requires-Dist: mypy==1.19.0
Dynamic: author
Dynamic: author-email
Dynamic: classifier
Dynamic: description
Dynamic: description-content-type
Dynamic: home-page
Dynamic: keywords
Dynamic: license
Dynamic: license-file
Dynamic: requires-dist
Dynamic: requires-python
Dynamic: summary
